{
  "season": "2025",
  "round": "9",
  "raceName": "Spanish Grand Prix",
  "driver": {
    "driverId": "piastri",
    "permanentNumber": "81",
    "code": "PIA",
    "url": "http://en.wikipedia.org/wiki/Oscar_Piastri",
    "givenName": "Oscar",
    "familyName": "Piastri",
    "dateOfBirth": "2001-04-06",
    "nationality": "Australian"
  },
  "constructor": {
    "constructorId": "mclaren",
    "url": "http://en.wikipedia.org/wiki/McLaren",
    "name": "McLaren",
    "nationality": "British"
  },
  "laps": [
    {
      "lap": 2,
      "time": "1:20.211",
      "duration": 80.211,
      "sector1": 24.207,
      "sector2": 32.317,
      "sector3": 23.687,
      "isPitLap": false
    },
    {
      "lap": 3,
      "time": "1:19.866",
      "duration": 79.866,
      "sector1": 23.812,
      "sector2": 31.867,
      "sector3": 24.187,
      "isPitLap": false
    },
    {
      "lap": 4,
      "time": "1:20.359",
      "duration": 80.359,
      "sector1": 24.104,
      "sector2": 32.173,
      "sector3": 24.082,
      "isPitLap": false
    },
    {
      "lap": 5,
      "time": "1:20.467",
      "duration": 80.467,
      "sector1": 24.036,
      "sector2": 32.363,
      "sector3": 24.068,
      "isPitLap": false
    },
    {
      "lap": 6,
      "time": "1:20.254",
      "duration": 80.254,
      "sector1": 23.854,
      "sector2": 32.345,
      "sector3": 24.055,
      "isPitLap": false
    },
    {
      "lap": 7,
      "time": "1:20.931",
      "duration": 80.931,
      "sector1": 24.007,
      "sector2": 32.591,
      "sector3": 24.333,
      "isPitLap": false
    },
    {
      "lap": 8,
      "time": "1:20.828",
      "duration": 80.828,
      "sector1": 24.044,
      "sector2": 32.55,
      "sector3": 24.234,
      "isPitLap": false
    },
    {
      "lap": 9,
      "time": "1:20.767",
      "duration": 80.767,
      "sector1": 24.017,
      "sector2": 32.505,
      "sector3": 24.245,
      "isPitLap": false
    },
    {
      "lap": 10,
      "time": "1:20.890",
      "duration": 80.89,
      "sector1": 23.925,
      "sector2": 32.469,
      "sector3": 24.496,
      "isPitLap": false
    },
    {
      "lap": 11,
      "time": "1:21.136",
      "duration": 81.136,
      "sector1": 24.081,
      "sector2": 32.577,
      "sector3": 24.478,
      "isPitLap": false
    },
    {
      "lap": 12,
      "time": "1:21.091",
      "duration": 81.091,
      "sector1": 24.007,
      "sector2": 32.636,
      "sector3": 24.448,
      "isPitLap": false
    },
    {
      "lap": 13,
      "time": "1:21.033",
      "duration": 81.033,
      "sector1": 24.097,
      "sector2": 32.618,
      "sector3": 24.318,
      "isPitLap": false
    },
    {
      "lap": 14,
      "time": "1:20.780",
      "duration": 80.78,
      "sector1": 23.896,
      "sector2": 32.572,
      "sector3": 24.312,
      "isPitLap": false
    },
    {
      "lap": 15,
      "time": "1:20.804",
      "duration": 80.804,
      "sector1": 23.883,
      "sector2": 32.601,
      "sector3": 24.32,
      "isPitLap": false
    },
    {
      "lap": 16,
      "time": "1:20.659",
      "duration": 80.659,
      "sector1": 23.985,
      "sector2": 32.41,
      "sector3": 24.264,
      "isPitLap": false
    },
    {
      "lap": 17,
      "time": "1:20.657",
      "duration": 80.657,
      "sector1": 23.912,
      "sector2": 32.432,
      "sector3": 24.313,
      "isPitLap": false
    },
    {
      "lap": 18,
      "time": "1:20.693",
      "duration": 80.693,
      "sector1": 23.795,
      "sector2": 32.529,
      "sector3": 24.369,
      "isPitLap": false
    },
    {
      "lap": 19,
      "time": "1:20.850",
      "duration": 80.85,
      "sector1": 23.806,
      "sector2": 32.673,
      "sector3": 24.371,
      "isPitLap": false
    },
    {
      "lap": 20,
      "time": "1:21.126",
      "duration": 81.126,
      "sector1": 23.87,
      "sector2": 32.832,
      "sector3": 24.424,
      "isPitLap": false
    },
    {
      "lap": 21,
      "time": "1:21.471",
      "duration": 81.471,
      "sector1": 23.83,
      "sector2": 33.006,
      "sector3": 24.635,
      "isPitLap": false
    },
    {
      "lap": 22,
      "time": "1:25.235",
      "duration": 85.235,
      "sector1": 24.005,
      "sector2": 32.982,
      "sector3": 28.248,
      "isPitLap": false
    },
    {
      "lap": 23,
      "time": "1:38.679",
      "duration": 98.679,
      "sector1": 42.367,
      "sector2": 32.392,
      "sector3": 23.92,
      "isPitLap": true
    },
    {
      "lap": 24,
      "time": "1:19.985",
      "duration": 79.985,
      "sector1": 23.897,
      "sector2": 32.083,
      "sector3": 24.005,
      "isPitLap": false
    },
    {
      "lap": 25,
      "time": "1:19.850",
      "duration": 79.85,
      "sector1": 23.825,
      "sector2": 32.069,
      "sector3": 23.956,
      "isPitLap": false
    },
    {
      "lap": 26,
      "time": "1:19.913",
      "duration": 79.913,
      "sector1": 23.848,
      "sector2": 32.111,
      "sector3": 23.954,
      "isPitLap": false
    },
    {
      "lap": 27,
      "time": "1:19.749",
      "duration": 79.749,
      "sector1": 23.682,
      "sector2": 31.985,
      "sector3": 24.082,
      "isPitLap": false
    },
    {
      "lap": 28,
      "time": "1:19.904",
      "duration": 79.904,
      "sector1": 23.747,
      "sector2": 32.087,
      "sector3": 24.07,
      "isPitLap": false
    },
    {
      "lap": 29,
      "time": "1:19.919",
      "duration": 79.919,
      "sector1": 23.642,
      "sector2": 32.072,
      "sector3": 24.205,
      "isPitLap": false
    },
    {
      "lap": 30,
      "time": "1:19.807",
      "duration": 79.807,
      "sector1": 23.655,
      "sector2": 32.076,
      "sector3": 24.076,
      "isPitLap": false
    },
    {
      "lap": 31,
      "time": "1:19.719",
      "duration": 79.719,
      "sector1": 23.677,
      "sector2": 31.965,
      "sector3": 24.077,
      "isPitLap": false
    },
    {
      "lap": 32,
      "time": "1:19.983",
      "duration": 79.983,
      "sector1": 23.732,
      "sector2": 32.09,
      "sector3": 24.161,
      "isPitLap": false
    },
    {
      "lap": 33,
      "time": "1:20.387",
      "duration": 80.387,
      "sector1": 23.835,
      "sector2": 32.204,
      "sector3": 24.348,
      "isPitLap": false
    },
    {
      "lap": 34,
      "time": "1:20.474",
      "duration": 80.474,
      "sector1": 24.056,
      "sector2": 32.266,
      "sector3": 24.152,
      "isPitLap": false
    },
    {
      "lap": 35,
      "time": "1:20.150",
      "duration": 80.15,
      "sector1": 23.796,
      "sector2": 32.219,
      "sector3": 24.135,
      "isPitLap": false
    },
    {
      "lap": 36,
      "time": "1:20.129",
      "duration": 80.129,
      "sector1": 23.762,
      "sector2": 32.053,
      "sector3": 24.314,
      "isPitLap": false
    },
    {
      "lap": 37,
      "time": "1:20.457",
      "duration": 80.457,
      "sector1": 23.749,
      "sector2": 32.436,
      "sector3": 24.272,
      "isPitLap": false
    },
    {
      "lap": 38,
      "time": "1:19.681",
      "duration": 79.681,
      "sector1": 23.495,
      "sector2": 32.071,
      "sector3": 24.115,
      "isPitLap": false
    },
    {
      "lap": 39,
      "time": "1:19.945",
      "duration": 79.945,
      "sector1": 23.596,
      "sector2": 32.134,
      "sector3": 24.215,
      "isPitLap": false
    },
    {
      "lap": 40,
      "time": "1:20.293",
      "duration": 80.293,
      "sector1": 23.622,
      "sector2": 32.26,
      "sector3": 24.411,
      "isPitLap": false
    },
    {
      "lap": 41,
      "time": "1:20.125",
      "duration": 80.125,
      "sector1": 23.61,
      "sector2": 32.192,
      "sector3": 24.323,
      "isPitLap": false
    },
    {
      "lap": 42,
      "time": "1:20.141",
      "duration": 80.141,
      "sector1": 23.559,
      "sector2": 32.464,
      "sector3": 24.118,
      "isPitLap": false
    },
    {
      "lap": 43,
      "time": "1:19.489",
      "duration": 79.489,
      "sector1": 23.26,
      "sector2": 32.06,
      "sector3": 24.169,
      "isPitLap": false
    },
    {
      "lap": 44,
      "time": "1:19.694",
      "duration": 79.694,
      "sector1": 23.633,
      "sector2": 32.109,
      "sector3": 23.952,
      "isPitLap": false
    },
    {
      "lap": 45,
      "time": "1:19.438",
      "duration": 79.438,
      "sector1": 23.473,
      "sector2": 32.026,
      "sector3": 23.939,
      "isPitLap": false
    },
    {
      "lap": 46,
      "time": "1:19.235",
      "duration": 79.235,
      "sector1": 23.355,
      "sector2": 31.911,
      "sector3": 23.969,
      "isPitLap": false
    },
    {
      "lap": 47,
      "time": "1:19.630",
      "duration": 79.63,
      "sector1": 23.435,
      "sector2": 32.138,
      "sector3": 24.057,
      "isPitLap": false
    },
    {
      "lap": 48,
      "time": "1:19.378",
      "duration": 79.378,
      "sector1": 23.414,
      "sector2": 32.01,
      "sector3": 23.954,
      "isPitLap": false
    },
    {
      "lap": 49,
      "time": "1:23.190",
      "duration": 83.19,
      "sector1": 23.405,
      "sector2": 32.173,
      "sector3": 27.612,
      "isPitLap": false
    },
    {
      "lap": 50,
      "time": "1:37.740",
      "duration": 97.74,
      "sector1": 42.176,
      "sector2": 31.785,
      "sector3": 23.779,
      "isPitLap": true
    },
    {
      "lap": 51,
      "time": "1:18.780",
      "duration": 78.78,
      "sector1": 23.425,
      "sector2": 31.573,
      "sector3": 23.782,
      "isPitLap": false
    },
    {
      "lap": 52,
      "time": "1:18.796",
      "duration": 78.796,
      "sector1": 23.254,
      "sector2": 31.783,
      "sector3": 23.759,
      "isPitLap": false
    },
    {
      "lap": 53,
      "time": "1:17.885",
      "duration": 77.885,
      "sector1": 23.183,
      "sector2": 31.381,
      "sector3": 23.321,
      "isPitLap": false
    },
    {
      "lap": 54,
      "time": "1:17.766",
      "duration": 77.766,
      "sector1": 23.099,
      "sector2": 31.335,
      "sector3": 23.332,
      "isPitLap": false
    },
    {
      "lap": 55,
      "time": "1:31.156",
      "duration": 91.156,
      "sector1": 23.051,
      "sector2": 34.302,
      "sector3": 33.803,
      "isPitLap": false
    },
    {
      "lap": 56,
      "time": "2:28.794",
      "duration": 148.794,
      "sector1": 48.336,
      "sector2": 59.483,
      "sector3": 40.975,
      "isPitLap": true
    },
    {
      "lap": 57,
      "time": "2:05.517",
      "duration": 125.517,
      "sector1": 38.853,
      "sector2": 50.521,
      "sector3": 36.143,
      "isPitLap": false
    },
    {
      "lap": 58,
      "time": "2:11.884",
      "duration": 131.884,
      "sector1": 40.221,
      "sector2": 49.47,
      "sector3": 42.193,
      "isPitLap": false
    },
    {
      "lap": 59,
      "time": "2:03.898",
      "duration": 123.898,
      "sector1": 39.114,
      "sector2": 48.246,
      "sector3": 36.538,
      "isPitLap": false
    },
    {
      "lap": 60,
      "time": "2:03.756",
      "duration": 123.756,
      "sector1": 35.169,
      "sector2": 47.306,
      "sector3": 41.281,
      "isPitLap": false
    },
    {
      "lap": 61,
      "time": "1:15.743",
      "duration": 75.743,
      "sector1": 22.645,
      "sector2": 30.476,
      "sector3": 22.622,
      "isPitLap": false
    },
    {
      "lap": 62,
      "time": "1:15.933",
      "duration": 75.933,
      "sector1": 22.74,
      "sector2": 30.59,
      "sector3": 22.603,
      "isPitLap": false
    },
    {
      "lap": 63,
      "time": "1:16.377",
      "duration": 76.377,
      "sector1": 22.626,
      "sector2": 30.748,
      "sector3": 23.003,
      "isPitLap": false
    },
    {
      "lap": 64,
      "time": "1:16.580",
      "duration": 76.58,
      "sector1": 22.698,
      "sector2": 30.883,
      "sector3": 22.999,
      "isPitLap": false
    },
    {
      "lap": 65,
      "time": "1:16.994",
      "duration": 76.994,
      "sector1": 22.605,
      "sector2": 31.169,
      "sector3": 23.22,
      "isPitLap": false
    },
    {
      "lap": 66,
      "time": "1:17.445",
      "duration": 77.445,
      "sector1": 22.694,
      "sector2": 31.406,
      "sector3": 23.345,
      "isPitLap": false
    }
  ],
  "lapError": null
}